include/define.svh
`ifndef DEFINE_SVH
`define DEFINE_SVH

// n = 64 , modular = 257, radix=16
`timescale 10ns / 1ps
`define D_width 32
`define double_d_width `D_width*2

`define degree 8192
`define Radix 16
`define Radix_width $clog2(`Radix)
`define degree_width $clog2(`degree)

`define BN `Radix
`define MA `degree/`BN
`define BANK_width $clog2(`BN)
`define MA_width $clog2(`MA)
`define delta $clog2(`Radix)                            //logr
`define bank_idx_upper_bound  $clog2(`degree) / `delta  //logr^N


`define radix_k1 4
`define radix_k2 1
`define k ( $clog2(`degree) - `radix_k2) / `radix_k1
`define logn $clog2(`degree)
//-------barrett precomputing value-----
`define pre_computing_width `D_width+3                  // D_width+3
`define precompute 35'd11453246119


`endif

src/memory_rtl.sv
`include "../include/define.svh"

module memory_rtl(
    input [`D_width-1:0] data_in,
    input [`D_width-1:0] BN_idx,
    input [`MA_width-1:0] MA_idx,

    input r_enable,
    input w_enable,
    input clk,
    input rst,

    output logic [`D_width-1:0] memory_ans

);


    logic [`D_width-1:0] memory_array [0:`BN-1][0:`MA-1];
 

    always_ff @( posedge clk or posedge rst ) begin
        integer i, j;
        if (rst) begin
            for (i = 0; i<`BN; i=i+1) begin
                for (j = 0; j<`MA ; j=j+1 ) begin
                    memory_array[i][j] <= 'd0;
                end
            end
        end 
    end
 

    always_ff@(posedge clk or posedge rst) begin
        case({r_enable, w_enable})
            'b10: begin
                memory_ans <= memory_array[BN_idx][MA_idx];
            end
            'b01: begin
                memory_array[BN_idx][MA_idx] <= data_in;
            end
            'b11: begin
                memory_ans <= memory_array[BN_idx][MA_idx];
                memory_array[BN_idx][MA_idx] <= data_in;
            end
            default: begin
                memory_ans <= memory_ans;
                memory_array[BN_idx][MA_idx] <= memory_array[BN_idx][MA_idx];
            end
        endcase
    end



endmodule

sim/testbench/MEM_tb.sv
`include "../include/define.svh"
`define CYCLE 10
`include "memory_rtl.sv"

module Testbench ();
    logic clk;
    logic rst;
    logic r_enable;
    logic w_enable;

    logic [`D_width-1:0] data_in;
    logic [`D_width-1:0] BN_idx;
    logic [`MA_width-1:0] MA_idx;

    logic [`D_width-1:0] memory_ans;

    logic [`BANK_width-1:0] BN_golden [0:`degree-1];
    logic [`MA_width-1:0] MA_golden [0:`degree-1];
    logic [`D_width-1:0] data_golden [0:`degree-1];

    logic [`D_width-1:0] cnt;
    integer num = 0;
    integer err = 0;
    logic flag = 0;
    integer i;

    memory_rtl mem(
        .data_in(data_in),
        .BN_idx(BN_idx),
        .MA_idx(MA_idx),

        .r_enable(r_enable),
        .w_enable(w_enable),
        .clk(clk),
        .rst(rst),
        .memory_ans(memory_ans)
    );

    initial begin
        $readmemh("../sim/data_file/mem/mem_algo_bank.txt", BN_golden);  
        $readmemh("../sim/data_file/mem/mem_algo_MA.txt", MA_golden);  
        $readmemh("../sim/data_file/mem/mem_algo_data.txt", data_golden);  
    end


    always #(`CYCLE/2) clk = ~clk;

    initial begin
        #0
        clk = 0; 
        rst = 1;
        i = 0;
        #`CYCLE rst = 0;
    end


    always_ff @( posedge clk or posedge rst ) begin
        if (rst) begin
            cnt <= 'd0;            
        end else begin
            if (cnt == `degree - 1) begin
                cnt <= cnt;
            end else begin
                cnt <= cnt + 'd1;
            end
        end
    end

    initial begin
        for(int i=0; i<`BN; i = i+1) begin
            for (int j =0 ;j<`MA ;j=j+1 ) begin
                data_in <= i*`BN + j;
                BN_idx <= i;
                MA_idx <= j;
                r_enable <= 'd0;
                w_enable <= 'd1;
                flag = flag;
                #`CYCLE;
            end
        end
        flag = 1;
    end

    initial begin
        #(`CYCLE*8192);
        for(int i=0; i<`degree; i = i+1) begin
            data_in <= 'd0;
            BN_idx <= BN_golden[i];
            MA_idx <= MA_golden[i];
            r_enable <= 'd0;
            w_enable <= 'd1;
            #`CYCLE;
            if (memory_ans == data_golden[i]) begin
                $display("%d data is correct, your (BN, MA, data) = (%d, %d, %d), golden (BN, MA, data) = (%d, %d, %d)",
                            num, BN_idx, MA_idx, memory_ans, BN_golden[i], MA_golden[i], data_golden[i]);
            end else begin
                $display("%d data is failed!!!!, your (BN, MA, data) = (%d, %d, %d), golden (BN, MA, data) = (%d, %d, %d)",
                            num, BN_idx, MA_idx, memory_ans, BN_golden[i], MA_golden[i], data_golden[i]);
                err = err + 1;
            end
            num = num + 1;
        end
        result(err, num);
        #(`CYCLE*`MAX) $finish;
    end


    initial begin
        $dumpfile("MEM_tb.vcd");
        $dumpvars;
        #(`CYCLE*`MAX)
        $finish;
    end
    task result;
    input integer err;
    input integer num;
    integer rf;
    begin
      if (err === 0)
      begin
        $display("\n");
        $display("\n");
        $display("        ****************************               ");
        $display("        **                        **       |\__||  ");
        $display("        **  Congratulations !!    **      / O.O  | ");
        $display("        **                        **    /_____   | ");
        $display("        **  Simulation PASS!!     **   /^ ^ ^ \\  |");
        $display("        **                        **  |^ ^ ^ ^ |w| ");
        $display("        ****************************   \\m___m__|_|");
        $display("\n");
      end
      else
      begin
        $display("\n");
        $display("\n");
        $display("        ****************************               ");
        $display("        **                        **       |\__||  ");
        $display("        **  OOPS!!                **      / X,X  | ");
        $display("        **                        **    /_____   | ");
        $display("        **  Simulation Failed!!   **   /^ ^ ^ \\  |");
        $display("        **                        **  |^ ^ ^ ^ |w| ");
        $display("        ****************************   \\m___m__|_|");
        $display("         Totally has %d errors                     ", err); 
        $display("\n");
      end
    end
  endtask
  
endmodule

build/MEM_tb.vcd
$date
    Jul  2, 2022  15:43:58
$end
$version
    TOOL:	ncsim	15.20-s084
$end
$timescale
    1 ps
$end

$scope module Testbench $end
$var reg       1 !    clk  $end
$var reg       1 "    rst  $end
$var reg       1 #    r_enable  $end
$var reg       1 $    w_enable  $end
$var reg      32 %    data_in [31:0] $end
$var reg      32 &    BN_idx [31:0] $end
$var reg       9 '    MA_idx [8:0] $end
$var reg      32 (    memory_ans [31:0] $end
$var reg      32 )    cnt [31:0] $end
$var integer  32 *    num  $end
$var integer  32 +    err  $end
$var reg       1 ,    flag  $end
$var integer  32 -    i  $end

$scope module mem $end
$var wire     32 .    data_in [31:0] $end
$var wire     32 /    BN_idx [31:0] $end
$var wire      9 0    MA_idx [8:0] $end
$var wire      1 1    r_enable  $end
$var wire      1 2    w_enable  $end
$var wire      1 3    clk  $end
$var wire      1 4    rst  $end
$var reg      32 5    memory_ans [31:0] $end

$scope begin unmblk1 $end
$var integer  32 6    i  $end
$var integer  32 7    j  $end
$upscope $end

$upscope $end


$scope task result $end
$var integer  32 8    err  $end
$var integer  32 9    num  $end
$var integer  32 :    rf  $end
$upscope $end

$upscope $end

$enddefinitions $end
$dumpvars
0!
1"
0#
1$
b0 %
b0 &
b0 '
bx (
b0 )
b0 *
b0 +
0,
b0 -
b0 .
b0 /
b0 0
01
12
03
14
bx 5
b10000 6
b1000000000 7
bx 8
bx 9
bx :
$end
#60000
1!
13
#120000
0"
0!
03
04
b1 %
b1 '
b1 0
b1 .
#180000
1!
13
b1 )
#240000
0!
03
b10 %
b10 '
b10 0
b10 .
#300000
1!
13
b10 )
#360000
0!
03
b11 %
b11 '
b11 0
b11 .
#420000
1!
13
b11 )
#480000
0!
03
b100 %
b100 '
b100 0
b100 .
#540000
1!
13
b100 )
#600000
0!
03
b101 %
b101 '
b101 0
b101 .
#660000
1!
13
b101 )
#720000
0!
03
b110 %
b110 '
b110 0
b110 .
#780000
1!
13
b110 )
#840000
0!
03
b111 %
b111 '
b111 0
b111 .
#900000
1!
13
b111 )
#960000
0!
03
b1000 %
b1000 '
b1000 0
b1000 .
#1020000
1!
13
b1000 )
#1080000
0!
03
b1001 %
b1001 '
b1001 0
b1001 .
#1140000
1!
13
b1001 )
#1200000
0!
03
b1010 %
b1010 '
b1010 0
b1010 .
#1260000
1!
13
b1010 )
#1320000
0!
03
b1011 %
b1011 '
b1011 0
b1011 .
#1380000
1!
13
b1011 )
#1440000
0!
03
b1100 %
b1100 '
b1100 0
b1100 .
#1500000
1!
13
b1100 )
#1560000
0!
03
b1101 %
b1101 '
b1101 0
b1101 .
#1620000
1!
13
b1101 )
#1680000
0!
03
b1110 %
b1110 '
b1110 0
b1110 .
#1740000
1!
13
b1110 )
#1800000
0!
03
b1111 %
b1111 '
b1111 0
b1111 .
#1860000
1!
13
b1111 )
#1920000
0!
03
b10000 %
b10000 '
b10000 0
b10000 .
#1980000
1!
13
b10000 )
#2040000
0!
03
b10001 %
b10001 '
b10001 0
b10001 .
#2100000
1!
13
b10001 )
#2160000
0!
03
b10010 %
b10010 '
b10010 0
b10010 .
#2220000
1!
13
b10010 )
#2280000
0!
03
b10011 %
b10011 '
b10011 0
b10011 .
#2340000
1!
13
b10011 )
#2400000
0!
03
b10100 %
b10100 '
b10100 0
b10100 .
#2460000
1!
13
b10100 )
#2520000
0!
03
b10101 %
b10101 '
b10101 0
b10101 .
#2580000
1!
13
b10101 )
#2640000
0!
03
b10110 %
b10110 '
b10110 0
b10110 .
#2700000
1!
13
b10110 )
#2760000
0!
03
b10111 %
b10111 '
b10111 0
b10111 .
#2820000
1!
13
b10111 )
#2880000
0!
03
b11000 %
b11000 '
b11000 0
b11000 .
#2940000
1!
13
b11000 )
#3000000
0!
03
b11001 %
b11001 '
b11001 0
b11001 .
#3060000
1!
13
b11001 )
#3120000
0!
03
b11010 %
b11010 '
b11010 0
b11010 .
#3180000
1!
13
b11010 )
#3240000
0!
03
b11011 %
b11011 '
b11011 0
b11011 .
#3300000
1!
13
b11011 )
#3360000
0!
03
b11100 %
b11100 '
b11100 0
b11100 .
#3420000
1!
13
b11100 )
#3480000
0!
03
b11101 %
b11101 '
b11101 0
b11101 .
#3540000
1!
13
b11101 )
#3600000
0!
03
b11110 %
b11110 '
b11110 0
b11110 .
#3660000
1!
13
b11110 )
#3720000
0!
03
b11111 %
b11111 '
b11111 0
b11111 .
#3780000
1!
13
b11111 )
#3840000
0!
03
b100000 %
b100000 '
b100000 0
b100000 .
#3900000
1!
13
b100000 )
#3960000
0!
03
b100001 %
b100001 '
b100001 0
b100001 .
#4020000
1!
13
b100001 )
#4080000
0!
03
b100010 %
b100010 '
b100010 0
b100010 .
#4140000
1!
13
b100010 )
#4200000
0!
03
b100011 %
b100011 '
b100011 0
b100011 .
#4260000
1!
13
b100011 )
#4320000
0!
03
b100100 %
b100100 '
b100100 0
b100100 .
#4380000
1!
13
b100100 )
#4440000
0!
03
b100101 %
b100101 '
b100101 0
b100101 .
#4500000
1!
13
b100101 )
#4560000
0!
03
b100110 %
b100110 '
b100110 0
b100110 .
#4620000
1!
13
b100110 )
#4680000
0!
03
b100111 %
b100111 '
b100111 0
b100111 .
#4740000
1!
13
b100111 )
#4800000
0!
03
b101000 %
b101000 '
b101000 0
b101000 .
#4860000
1!
13
b101000 )
#4920000
0!
03
b101001 %
b101001 '
b101001 0
b101001 .
#4980000
1!
13
b101001 )
#5040000
0!
03
b101010 %
b101010 '
b101010 0
b101010 .
#5100000
1!
13
b101010 )
#5160000
0!
03
b101011 %
b101011 '
b101011 0
b101011 .
#5220000
1!
13
b101011 )
#5280000
0!
03
b101100 %
b101100 '
b101100 0
b101100 .
#5340000
1!
13
b101100 )
#5400000
0!
03
b101101 %
b101101 '
b101101 0
b101101 .
#5460000
1!
13
b101101 )
#5520000
0!
03
b101110 %
b101110 '
b101110 0
b101110 .
#5580000
1!
13
b101110 )
#5640000
0!
03
b101111 %
b101111 '
b101111 0
b101111 .
#5700000
1!
13
b101111 )
#5760000
0!
03
b110000 %
b110000 '
b110000 0
b110000 .
#5820000
1!
13
b110000 )
#5880000
0!
03
b110001 %
b110001 '
b110001 0
b110001 .
#5940000
1!
13
b110001 )
#6000000
0!
03
b110010 %
b110010 '
b110010 0
b110010 .
#6060000
1!
13
b110010 )
#6120000
0!
03
b110011 %
b110011 '
b110011 0
b110011 .
#6180000
1!
13
b110011 )
#6240000
0!
03
b110100 %
b110100 '
b110100 0
b110100 .
#6300000
1!
13
b110100 )
#6360000
0!
03
b110101 %
b110101 '
b110101 0
b110101 .
#6420000
1!
13
b110101 )
#6480000
0!
03
b110110 %
b110110 '
b110110 0
b110110 .
#6540000
1!
13
b110110 )
#6600000
0!
03
b110111 %
b110111 '
b110111 0
b110111 .
#6660000
1!
13
b110111 )
#6720000
0!
03
b111000 %
b111000 '
b111000 0
b111000 .
#6780000
1!
13
b111000 )
#6840000
0!
03
b111001 %
b111001 '
b111001 0
b111001 .
#6900000
1!
13
b111001 )
#6960000
0!
03
b111010 %
b111010 '
b111010 0
b111010 .
#7020000
1!
13
b111010 )
#7080000
0!
03
b111011 %
b111011 '
b111011 0
b111011 .
#7140000
1!
13
b111011 )
#7200000
0!
03
b111100 %
b111100 '
b111100 0
b111100 .
#7260000
1!
13
b111100 )
#7320000
0!
03
b111101 %
b111101 '
b111101 0
b111101 .
#7380000
1!
13
b111101 )
#7440000
0!
03
b111110 %
b111110 '
b111110 0
b111110 .
#7500000
1!
13
b111110 )
#7560000
0!
03
b111111 %
b111111 '
b111111 0
b111111 .
#7620000
1!
13
b111111 )
#7680000
0!
03
b1000000 %
b1000000 '
b1000000 0
b1000000 .
#7740000
1!
13
b1000000 )
#7800000
0!
03
b1000001 %
b1000001 '
b1000001 0
b1000001 .
#7860000
1!
13
b1000001 )
#7920000
0!
03
b1000010 %
b1000010 '
b1000010 0
b1000010 .
#7980000
1!
13
b1000010 )
#8040000
0!
03
b1000011 %
b1000011 '
b1000011 0
b1000011 .
#8100000
1!
13
b1000011 )
#8160000
0!
03
b1000100 %
b1000100 '
b1000100 0
b1000100 .
#8220000
1!
13
b1000100 )
#8280000
0!
03
b1000101 %
b1000101 '
b1000101 0
b1000101 .
#8340000
1!
13
b1000101 )
#8400000
0!
03
b1000110 %
b1000110 '
b1000110 0
b1000110 .
#8460000
1!
13
b1000110 )
#8520000
0!
03
b1000111 %
b1000111 '
b1000111 0
b1000111 .
#8580000
1!
13
b1000111 )
#8640000
0!
03
b1001000 %
b1001000 '
b1001000 0
b1001000 .
#8700000
1!
13
b1001000 )
#8760000
0!
03
b1001001 %
b1001001 '
b1001001 0
b1001001 .
#8820000
1!
13
b1001001 )
#8880000
0!
03
b1001010 %
b1001010 '
b1001010 0
b1001010 .
#8940000
1!
13
b1001010 )
#9000000
0!
03
b1001011 %
b1001011 '
b1001011 0
b1001011 .
#9060000
1!
13
b1001011 )
#9120000
0!
03
b1001100 %
b1001100 '
b1001100 0
b1001100 .
#9180000
1!
13
b1001100 )
#9240000
0!
03
b1001101 %
b1001101 '
b1001101 0
b1001101 .
#9300000
1!
13
b1001101 )
#9360000
0!
03
b1001110 %
b1001110 '
b1001110 0
b1001110 .
#9420000
1!
13
b1001110 )
#9480000
0!
03
b1001111 %
b1001111 '
b1001111 0
b1001111 .
#9540000
1!
13
b1001111 )
#9600000
0!
03
b1010000 %
b1010000 '
b1010000 0
b1010000 .
#9660000
1!
13
b1010000 )
#9720000
0!
03
b1010001 %
b1010001 '
b1010001 0
b1010001 .
#9780000
1!
13
b1010001 )
#9840000
0!
03
b1010010 %
b1010010 '
b1010010 0
b1010010 .
#9900000
1!
13
b1010010 )
#9960000
0!
03
b1010011 %
b1010011 '
b1010011 0
b1010011 .
#10020000
1!
13
b1010011 )
#10080000
0!
03
b1010100 %
b1010100 '
b1010100 0
b1010100 .
#10140000
1!
13
b1010100 )
#10200000
0!
03
b1010101 %
b1010101 '
b1010101 0
b1010101 .
#10260000
1!
13
b1010101 )
#10320000
0!
03
b1010110 %
b1010110 '
b1010110 0
b1010110 .
#10380000
1!
13
b1010110 )
#10440000
0!
03
b1010111 %
b1010111 '
b1010111 0
b1010111 .
#10500000
1!
13
b1010111 )
#10560000
0!
03
b1011000 %
b1011000 '
b1011000 0
b1011000 .
#10620000
1!
13
b1011000 )
#10680000
0!
03
b1011001 %
b1011001 '
b1011001 0
b1011001 .
#10740000
1!
13
b1011001 )
#10800000
0!
03
b1011010 %
b1011010 '
b1011010 0
b1011010 .
#10860000
1!
13
b1011010 )
#10920000
0!
03
b1011011 %
b1011011 '
b1011011 0
b1011011 .
#10980000
1!
13
b1011011 )
#11040000
0!
03
b1011100 %
b1011100 '
b1011100 0
b1011100 .
#11100000
1!
13
b1011100 )
#11160000
0!
03
b1011101 %
b1011101 '
b1011101 0
b1011101 .
#11220000
1!
13
b1011101 )
#11280000
0!
03
b1011110 %
b1011110 '
b1011110 0
b1011110 .
#11340000
1!
13
b1011110 )
#11400000
0!
03
b1011111 %
b1011111 '
b1011111 0
b1011111 .
#11460000
1!
13
b1011111 )
#11520000
0!
03
b1100000 %
b1100000 '
b1100000 0
b1100000 .
#11580000
1!
13
b1100000 )
#11640000
0!
03
b1100001 %
b1100001 '
b1100001 0
b1100001 .
#11700000
1!
13
b1100001 )
#11760000
0!
03
b1100010 %
b1100010 '
b1100010 0
b1100010 .
#11820000
1!
13
b1100010 )
#11880000
0!
03
b1100011 %
b1100011 '
b1100011 0
b1100011 .
#11940000
1!
13
b1100011 )
#12000000
0!
03
b1100100 %
b1100100 '
b1100100 0
b1100100 .
#12060000
1!
13
b1100100 )
#12120000
0!
03
b1100101 %
b1100101 '
b1100101 0
b1100101 .
#12180000
1!
13
b1100101 )
#12240000
0!
03
b1100110 %
b1100110 '
b1100110 0
b1100110 .
#12300000
1!
13
b1100110 )
#12360000
0!
03
b1100111 %
b1100111 '
b1100111 0
b1100111 .
#12420000
1!
13
b1100111 )
#12480000
0!
03
b1101000 %
b1101000 '
b1101000 0
b1101000 .
#12540000
1!
13
b1101000 )
#12600000
0!
03
b1101001 %
b1101001 '
b1101001 0
b1101001 .
#12660000
1!
13
b1101001 )
#12720000
0!
03
b1101010 %
b1101010 '
b1101010 0
b1101010 .
#12780000
1!
13
b1101010 )
#12840000
0!
03
b1101011 %
b1101011 '
b1101011 0
b1101011 .
#12900000
1!
13
b1101011 )
#12960000
0!
03
b1101100 %
b1101100 '
b1101100 0
b1101100 .
#13020000
1!
13
b1101100 )
#13080000
0!
03
b1101101 %
b1101101 '
b1101101 0
b1101101 .
#13140000
1!
13
b1101101 )
#13200000
0!
03
b1101110 %
b1101110 '
b1101110 0
b1101110 .
#13260000
1!
13
b1101110 )
#13320000
0!
03
b1101111 %
b1101111 '
b1101111 0
b1101111 .
#13380000
1!
13
b1101111 )
#13440000
0!
03
b1110000 %
b1110000 '
b1110000 0
b1110000 .
#13500000
1!
13
b1110000 )
#13560000
0!
03
b1110001 %
b1110001 '
b1110001 0
b1110001 .
#13620000
1!
13
b1110001 )
#13680000
0!
03
b1110010 %
b1110010 '
b1110010 0
b1110010 .
#13740000
1!
13
b1110010 )
#13800000
0!
03
b1110011 %
b1110011 '
b1110011 0
b1110011 .
#13860000
1!
13
b1110011 )
#13920000
0!
03
b1110100 %
b1110100 '
b1110100 0
b1110100 .
#13980000
1!
13
b1110100 )
#14040000
0!
03
b1110101 %
b1110101 '
b1110101 0
b1110101 .
#14100000
1!
13
b1110101 )
#14160000
0!
03
b1110110 %
b1110110 '
b1110110 0
b1110110 .
#14220000
1!
13
b1110110 )
#14280000
0!
03
b1110111 %
b1110111 '
b1110111 0
b1110111 .
#14340000
1!
13
b1110111 )
#14400000
0!
03
b1111000 %
b1111000 '
b1111000 0
b1111000 .
#14460000
1!
13
b1111000 )
#14520000
0!
03
b1111001 %
b1111001 '
b1111001 0
b1111001 .
#14580000
1!
13
b1111001 )
#14640000
0!
03
b1111010 %
b1111010 '
b1111010 0
b1111010 .
#14700000
1!
13
b1111010 )
#14760000
0!
03
b1111011 %
b1111011 '
b1111011 0
b1111011 .
#14820000
1!
13
b1111011 )
#14880000
0!
03
b1111100 %
b1111100 '
b1111100 0
b1111100 .
#14940000
1!
13
b1111100 )
#15000000
0!
03
b1111101 %
b1111101 '
b1111101 0
b1111101 .
#15060000
1!
13
b1111101 )
#15120000
0!
03
b1111110 %
b1111110 '
b1111110 0
b1111110 .
#15180000
1!
13
b1111110 )
#15240000
0!
03
b1111111 %
b1111111 '
b1111111 0
b1111111 .
#15300000
1!
13
b1111111 )
#15360000
0!
03
b10000000 %
b10000000 '
b10000000 0
b10000000 .
#15420000
1!
13
b10000000 )
#15480000
0!
03
b10000001 %
b10000001 '
b10000001 0
b10000001 .
#15540000
1!
13
b10000001 )
#15600000
0!
03
b10000010 %
b10000010 '
b10000010 0
b10000010 .
#15660000
1!
13
b10000010 )
#15720000
0!
03
b10000011 %
b10000011 '
b10000011 0
b10000011 .
#15780000
1!
13
b10000011 )
#15840000
0!
03
b10000100 %
b10000100 '
b10000100 0
b10000100 .
#15900000
1!
13
b10000100 )
#15960000
0!
03
b10000101 %
b10000101 '
b10000101 0
b10000101 .
#16020000
1!
13
b10000101 )
#16080000
0!
03
b10000110 %
b10000110 '
b10000110 0
b10000110 .
#16140000
1!
13
b10000110 )
#16200000
0!
03
b10000111 %
b10000111 '
b10000111 0
b10000111 .
#16260000
1!
13
b10000111 )
#16320000
0!
03
b10001000 %
b10001000 '
b10001000 0
b10001000 .
#16380000
1!
13
b10001000 )
#16440000
0!
03
b10001001 %
b10001001 '
b10001001 0
b10001001 .
#16500000
1!
13
b10001001 )
#16560000
0!
03
b10001010 %
b10001010 '
b10001010 0
b10001010 .
#16620000
1!
13
b10001010 )
#16680000
0!
03
b10001011 %
b10001011 '
b10001011 0
b10001011 .
#16740000
1!
13
b10001011 )
#16800000
0!
03
b10001100 %
b10001100 '
b10001100 0
b10001100 .
#16860000
1!
13
b10001100 )
#16920000
0!
03
b10001101 %
b10001101 '
b10001101 0
b10001101 .
#16980000
1!
13
b10001101 )
#17040000
0!
03
b10001110 %
b10001110 '
b10001110 0
b10001110 .
#17100000
1!
13
b10001110 )
#17160000
0!
03
b10001111 %
b10001111 '
b10001111 0
b10001111 .
#17220000
1!
13
b10001111 )
#17280000
0!
03
b10010000 %
b10010000 '
b10010000 0
b10010000 .
#17340000
1!
13
b10010000 )
#17400000
0!
03
b10010001 %
b10010001 '
b10010001 0
b10010001 .
#17460000
1!
13
b10010001 )
#17520000
0!
03
b10010010 %
b10010010 '
b10010010 0
b10010010 .
#17580000
1!
13
b10010010 )
#17640000
0!
03
b10010011 %
b10010011 '
b10010011 0
b10010011 .
#17700000
1!
13
b10010011 )
#17760000
0!
03
b10010100 %
b10010100 '
b10010100 0
b10010100 .
#17820000
1!
13
b10010100 )
#17880000
0!
03
b10010101 %
b10010101 '
b10010101 0
b10010101 .
#17940000
1!
13
b10010101 )
#18000000
0!
03
b10010110 %
b10010110 '
b10010110 0
b10010110 .
#18060000
1!
13
b10010110 )
#18120000
0!
03
b10010111 %
b10010111 '
b10010111 0
b10010111 .
#18180000
1!
13
b10010111 )
#18240000
0!
03
b10011000 %
b10011000 '
b10011000 0
b10011000 .
#18300000
1!
13
b10011000 )
#18360000
0!
03
b10011001 %
b10011001 '
b10011001 0
b10011001 .
#18420000
1!
13
b10011001 )
#18480000
0!
03
b10011010 %
b10011010 '
b10011010 0
b10011010 .
#18540000
1!
13
b10011010 )
#18600000
0!
03
b10011011 %
b10011011 '
b10011011 0
b10011011 .
#18660000
1!
13
b10011011 )
#18720000
0!
03
b10011100 %
b10011100 '
b10011100 0
b10011100 .
#18780000
1!
13
b10011100 )
#18840000
0!
03
b10011101 %
b10011101 '
b10011101 0
b10011101 .
#18900000
1!
13
b10011101 )
#18960000
0!
03
b10011110 %
b10011110 '
b10011110 0
b10011110 .
#19020000
1!
13
b10011110 )
#19080000
0!
03
b10011111 %
b10011111 '
b10011111 0
b10011111 .
#19140000
1!
13
b10011111 )
#19200000
0!
03
b10100000 %
b10100000 '
b10100000 0
b10100000 .
#19260000
1!
13
b10100000 )
#19320000
0!
03
b10100001 %
b10100001 '
b10100001 0
b10100001 .
#19380000
1!
13
b10100001 )
#19440000
0!
03
b10100010 %
b10100010 '
b10100010 0
b10100010 .
#19500000
1!
13
b10100010 )
#19560000
0!
03
b10100011 %
b10100011 '
b10100011 0
b10100011 .
#19620000
1!
13
b10100011 )
#19680000
0!
03
b10100100 %
b10100100 '
b10100100 0
b10100100 .
#19740000
1!
13
b10100100 )
#19800000
0!
03
b10100101 %
b10100101 '
b10100101 0
b10100101 .
#19860000
1!
13
b10100101 )
#19920000
0!
03
b10100110 %
b10100110 '
b10100110 0
b10100110 .
#19980000
1!
13
b10100110 )
#20040000
0!
03
b10100111 %
b10100111 '
b10100111 0
b10100111 .
#20100000
1!
13
b10100111 )
#20160000
0!
03
b10101000 %
b10101000 '
b10101000 0
b10101000 .
#20220000
1!
13
b10101000 )
#20280000
0!
03
b10101001 %
b10101001 '
b10101001 0
b10101001 .
#20340000
1!
13
b10101001 )
#20400000
0!
03
b10101010 %
b10101010 '
b10101010 0
b10101010 .
#20460000
1!
13
b10101010 )
#20520000
0!
03
b10101011 %
b10101011 '
b10101011 0
b10101011 .
#20580000
1!
13
b10101011 )
#20640000
0!
03
b10101100 %
b10101100 '
b10101100 0
b10101100 .
#20700000
1!
13
b10101100 )
#20760000
0!
03
b10101101 %
b10101101 '
b10101101 0
b10101101 .
#20820000
1!
13
b10101101 )
#20880000
0!
03
b10101110 %
b10101110 '
b10101110 0
b10101110 .
#20940000
1!
13
b10101110 )
#21000000
0!
03
b10101111 %
b10101111 '
b10101111 0
b10101111 .
#21060000
1!
13
b10101111 )
#21120000
0!
03
b10110000 %
b10110000 '
b10110000 0
b10110000 .
#21180000
1!
13
b10110000 )
#21240000
0!
03
b10110001 %
b10110001 '
b10110001 0
b10110001 .
#21300000
1!
13
b10110001 )
#21360000
0!
03
b10110010 %
b10110010 '
b10110010 0
b10110010 .
#21420000
1!
13
b10110010 )
#21480000
0!
03
b10110011 %
b10110011 '
b10110011 0
b10110011 .
#21540000
1!
13
b10110011 )
#21600000
0!
03
b10110100 %
b10110100 '
b10110100 0
b10110100 .
#21660000
1!
13
b10110100 )
#21720000
0!
03
b10110101 %
b10110101 '
b10110101 0
b10110101 .
#21780000
1!
13
b10110101 )
#21840000
0!
03
b10110110 %
b10110110 '
b10110110 0
b10110110 .
#21900000
1!
13
b10110110 )
#21960000
0!
03
b10110111 %
b10110111 '
b10110111 0
b10110111 .
#22020000
1!
13
b10110111 )
#22080000
0!
03
b10111000 %
b10111000 '
b10111000 0
b10111000 .
#22140000
1!
13
b10111000 )
#22200000
0!
03
b10111001 %
b10111001 '
b10111001 0
b10111001 .
#22260000
1!
13
b10111001 )
#22320000
0!
03
b10111010 %
b10111010 '
b10111010 0
b10111010 .
#22380000
1!
13
b10111010 )
#22440000
0!
03
b10111011 %
b10111011 '
b10111011 0
b10111011 .
#22500000
1!
13
b10111011 )
#22560000
0!
03
b10111100 %
b10111100 '
b10111100 0
b10111100 .
#22620000
1!
13
b10111100 )
#22680000
0!
03
b10111101 %
b10111101 '
b10111101 0
b10111101 .
#22740000
1!
13
b10111101 )
#22800000
0!
03
b10111110 %
b10111110 '
b10111110 0
b10111110 .
#22860000
1!
13
b10111110 )
#22920000
0!
03
b10111111 %
b10111111 '
b10111111 0
b10111111 .
#22980000
1!
13
b10111111 )
#23040000
0!
03
b11000000 %
b11000000 '
b11000000 0
b11000000 .
#23100000
1!
13
b11000000 )
#23160000
0!
03
b11000001 %
b11000001 '
b11000001 0
b11000001 .
#23220000
1!
13
b11000001 )
#23280000
0!
03
b11000010 %
b11000010 '
b11000010 0
b11000010 .
#23340000
1!
13
b11000010 )
#23400000
0!
03
b11000011 %
b11000011 '
b11000011 0
b11000011 .
#23460000
1!
13
b11000011 )
#23520000
0!
03
b11000100 %
b11000100 '
b11000100 0
b11000100 .
#23580000
1!
13
b11000100 )
#23640000
0!
03
b11000101 %
b11000101 '
b11000101 0
b11000101 .
#23700000
1!
13
b11000101 )
#23760000
0!
03
b11000110 %
b11000110 '
b11000110 0
b11000110 .
#23820000
1!
13
b11000110 )
#23880000
0!
03
b11000111 %
b11000111 '
b11000111 0
b11000111 .
#23940000
1!
13
b11000111 )
#24000000
0!
03
b11001000 %
b11001000 '
b11001000 0
b11001000 .
#24060000
1!
13
b11001000 )
#24120000
0!
03
b11001001 %
b11001001 '
b11001001 0
b11001001 .
#24180000
1!
13
b11001001 )
#24240000
0!
03
b11001010 %
b11001010 '
b11001010 0
b11001010 .
#24300000
1!
13
b11001010 )
#24360000
0!
03
b11001011 %
b11001011 '
b11001011 0
b11001011 .
#24420000
1!
13
b11001011 )
#24480000
0!
03
b11001100 %
b11001100 '
b11001100 0
b11001100 .
#24540000
1!
13
b11001100 )
#24600000
0!
03
b11001101 %
b11001101 '
b11001101 0
b11001101 .
#24660000
1!
13
b11001101 )
#24720000
0!
03
b11001110 %
b11001110 '
b11001110 0
b11001110 .
#24780000
1!
13
b11001110 )
#24840000
0!
03
b11001111 %
b11001111 '
b11001111 0
b11001111 .
#24900000
1!
13
b11001111 )
#24960000
0!
03
b11010000 %
b11010000 '
b11010000 0
b11010000 .
#25020000
1!
13
b11010000 )
#25080000
0!
03
b11010001 %
b11010001 '
b11010001 0
b11010001 .
#25140000
1!
13
b11010001 )
#25200000
0!
03
b11010010 %
b11010010 '
b11010010 0
b11010010 .
#25260000
1!
13
b11010010 )
#25320000
0!
03
b11010011 %
b11010011 '
b11010011 0
b11010011 .
#25380000
1!
13
b11010011 )
#25440000
0!
03
b11010100 %
b11010100 '
b11010100 0
b11010100 .
#25500000
1!
13
b11010100 )
#25560000
0!
03
b11010101 %
b11010101 '
b11010101 0
b11010101 .
#25620000
1!
13
b11010101 )
#25680000
0!
03
b11010110 %
b11010110 '
b11010110 0
b11010110 .
#25740000
1!
13
b11010110 )
#25800000
0!
03
b11010111 %
b11010111 '
b11010111 0
b11010111 .
#25860000
1!
13
b11010111 )
#25920000
0!
03
b11011000 %
b11011000 '
b11011000 0
b11011000 .
#25980000
1!
13
b11011000 )
